foop/__init__.py
foop/telemetry.py
foop-60.0.0.dist-info/METADATA
foop-60.0.0.dist-info/WHEEL
foop-60.0.0.dist-info/top_level.txt
foop-60.0.0.dist-info/RECORD
