Metadata-Version: 2.1
Name: foop
Version: 60.0.0
Summary: A simple Python package
Home-page: https://github.com/yourusername/foop
Author: Your Name
Author-email: your.email@example.com
Classifier: Programming Language :: Python :: 3
Classifier: License :: OSI Approved :: MIT License
Classifier: Operating System :: OS Independent
Requires-Dist: requests>=2.25.0
